LICENSE.txt
MANIFEST.in
README.md
setup.py
doc/Makefile
doc/source/conf.py
doc/source/index.rst
doc/source/reference/index.rst
doc/sphinxext/LICENSE.txt
doc/sphinxext/docscrape.py
doc/sphinxext/docscrape_sphinx.py
doc/sphinxext/numpydoc.py
examples/ascii.py
examples/graph_formats.py
examples/kuratowski.py
examples/networkx_draw.py
examples/networkx_interface.py
examples/pgraph_class.py
examples/write_adjlist.py
planarity/__init__.py
planarity/cplanarity.pxd
planarity/planarity.c
planarity/planarity.pyx
planarity/planarity_functions.py
planarity/planarity_networkx.py
planarity.egg-info/PKG-INFO
planarity.egg-info/SOURCES.txt
planarity.egg-info/dependency_links.txt
planarity.egg-info/not-zip-safe
planarity.egg-info/top_level.txt
planarity/src/appconst.h
planarity/src/graph.h
planarity/src/graphDFSUtils.c
planarity/src/graphDrawPlanar.c
planarity/src/graphDrawPlanar.h
planarity/src/graphDrawPlanar.private.h
planarity/src/graphDrawPlanar_Extensions.c
planarity/src/graphEmbed.c
planarity/src/graphExtensions.c
planarity/src/graphExtensions.h
planarity/src/graphExtensions.private.h
planarity/src/graphFunctionTable.h
planarity/src/graphIO.c
planarity/src/graphIsolator.c
planarity/src/graphK23Search.c
planarity/src/graphK23Search.h
planarity/src/graphK23Search.private.h
planarity/src/graphK23Search_Extensions.c
planarity/src/graphK33Search.c
planarity/src/graphK33Search.h
planarity/src/graphK33Search.private.h
planarity/src/graphK33Search_Extensions.c
planarity/src/graphK4Search.c
planarity/src/graphK4Search.h
planarity/src/graphK4Search.private.h
planarity/src/graphK4Search_Extensions.c
planarity/src/graphNonplanar.c
planarity/src/graphOuterplanarObstruction.c
planarity/src/graphStructures.h
planarity/src/graphTests.c
planarity/src/graphUtils.c
planarity/src/listcoll.c
planarity/src/listcoll.h
planarity/src/planarity.c
planarity/src/planarity.h
planarity/src/planarityCommandLine.c
planarity/src/planarityRandomGraphs.c
planarity/src/planaritySpecificGraph.c
planarity/src/planarityUtils.c
planarity/src/platformTime.h
planarity/src/stack.c
planarity/src/stack.h
planarity/src/strbuf.c
planarity/src/strbuf.h
tests/test_planarity.py
