Metadata-Version: 2.1
Name: planarity
Version: 0.6
Summary: Graph planarity tools.
Home-page: https://github.com/hagberg/planarity/
Download-URL: https://pypi.python.org/pypi/planarity
Author: Aric Hagberg
Author-email: aric.hagberg@gmail.com
Maintainer: Aric Hagberg
Maintainer-email: aric.hagberg@gmail.com
License: BSD
Classifier: Development Status :: 4 - Beta
Classifier: Intended Audience :: Developers
Classifier: Intended Audience :: Science/Research
Classifier: License :: OSI Approved :: BSD License
Classifier: Operating System :: OS Independent
Classifier: Programming Language :: Python :: 2
Classifier: Programming Language :: Python :: 2.7
Classifier: Programming Language :: Python :: 3
Classifier: Programming Language :: Python :: 3.10
Classifier: Programming Language :: Python :: 3.11
Classifier: Programming Language :: Python :: 3.12
Classifier: Topic :: Software Development :: Libraries :: Python Modules
Classifier: Topic :: Scientific/Engineering :: Information Analysis
Classifier: Topic :: Scientific/Engineering :: Mathematics
Classifier: Topic :: Scientific/Engineering :: Physics
License-File: LICENSE.txt
